gister/__init__.py
gister/__main__.py
gister/cli.py
gister/context.py
gister/errors.py
gister/gister.py
gister/runner.py
gister/version.py
gister/builder/__init__.py
gister/builder/command.py
gister/git/__init__.py
gister/git/environment.py
gister/log/__init__.py
gister/log/logger.py
gister/log/print.py
gister/parser/__init__.py
gister/parser/yamlfile.py
gister/steps/__init__.py
gister/steps/gitenv.py
gister/utils/__init__.py
gister/utils/asserts.py
gister/utils/text.py
gister_cli-0.0.6.dist-info/METADATA
gister_cli-0.0.6.dist-info/WHEEL
gister_cli-0.0.6.dist-info/entry_points.txt
gister_cli-0.0.6.dist-info/top_level.txt
gister_cli-0.0.6.dist-info/RECORD
