Metadata-Version: 2.1
Name: gister-cli
Version: 0.0.6
Summary: A awesome cli project.
Author: Josh Andres
Author-email: josh.an.bas@gmail.com
Classifier: Programming Language :: Python :: 3
Classifier: Operating System :: OS Independent
Requires-Python: >=3.6
Requires-Dist: requests
Requires-Dist: ruamel.yaml ==0.17.17
Requires-Dist: importlib ; python_version == "3.6"
